distil_whisper_fastrtc/__init__.py
distil_whisper_fastrtc/model.py
distil_whisper_fastrtc/utils.py
distil_whisper_fastrtc-0.1.0.post1.dist-info/LICENSE
distil_whisper_fastrtc-0.1.0.post1.dist-info/METADATA
distil_whisper_fastrtc-0.1.0.post1.dist-info/WHEEL
distil_whisper_fastrtc-0.1.0.post1.dist-info/top_level.txt
distil_whisper_fastrtc-0.1.0.post1.dist-info/RECORD
