Metadata-Version: 2.2
Name: distil-whisper-fastrtc
Version: 0.1.0.post1
Summary: Distil-Whisper wrapper for FastRTC speech-to-text
Author-email: Codeblockz <ryan.a.ellis.1@gmail.com>
License: MIT
Project-URL: Homepage, https://github.com/Codeblockz/distil-whisper-FastRTC
Project-URL: Bug Tracker, https://github.com/Codeblockz/distil-whisper-fastrtc/issues
Classifier: Programming Language :: Python :: 3
Classifier: License :: OSI Approved :: MIT License
Classifier: Operating System :: OS Independent
Requires-Python: >=3.8
License-File: LICENSE
Requires-Dist: numpy>=1.20.0
Requires-Dist: torch>=1.10.0
Requires-Dist: transformers>=4.30.0
Requires-Dist: accelerate>=0.20.0
Requires-Dist: click>=8.0.0
Provides-Extra: dev
Requires-Dist: pytest>=7.0.0; extra == "dev"
Requires-Dist: black>=23.0.0; extra == "dev"
Requires-Dist: isort>=5.0.0; extra == "dev"
Provides-Extra: audio
Requires-Dist: librosa>=0.9.0; extra == "audio"
